odoo/addons/sale_subscription_period_discount/LICENSE
odoo/addons/sale_subscription_period_discount/README.rst
odoo/addons/sale_subscription_period_discount/__init__.py
odoo/addons/sale_subscription_period_discount/__manifest__.py
odoo/addons/sale_subscription_period_discount/demo/sale_subscription_plan_demo.xml
odoo/addons/sale_subscription_period_discount/i18n/de.po
odoo/addons/sale_subscription_period_discount/images/screen.png
odoo/addons/sale_subscription_period_discount/migrations/18.0.1.0.0/pre-migrate.py
odoo/addons/sale_subscription_period_discount/models/__init__.py
odoo/addons/sale_subscription_period_discount/models/sale_order.py
odoo/addons/sale_subscription_period_discount/models/sale_order_line.py
odoo/addons/sale_subscription_period_discount/models/sale_subscription_plan.py
odoo/addons/sale_subscription_period_discount/security/ir.model.access.csv
odoo/addons/sale_subscription_period_discount/static/description/icon.png
odoo/addons/sale_subscription_period_discount/static/description/index.html
odoo/addons/sale_subscription_period_discount/tests/TEST_INSTRUCTIONS.rst
odoo/addons/sale_subscription_period_discount/views/sale_subscription.xml
odoo/addons/sale_subscription_period_discount/views/sale_subscription_plan.xml
odoo_addon_sale_subscription_period_discount-18.0.1.0.0.dist-info/METADATA
odoo_addon_sale_subscription_period_discount-18.0.1.0.0.dist-info/WHEEL
odoo_addon_sale_subscription_period_discount-18.0.1.0.0.dist-info/top_level.txt
odoo_addon_sale_subscription_period_discount-18.0.1.0.0.dist-info/RECORD
