Metadata-Version: 2.1
Name: odoo-addon-sale_subscription_period_discount
Version: 18.0.1.0.0
Requires-Python: >=3.10
Requires-Dist: odoo==18.0.*
Summary: Apply discounts on subscription periods.
Home-page: https://www.mint-system.ch/
License: OPL-1
Author: Mint System GmbH
Classifier: Programming Language :: Python
Classifier: Framework :: Odoo
Classifier: Framework :: Odoo :: 18.0
